.gitignore
AUTHORS
CODE_OF_CONDUCT.md
COPYING
MANIFEST.in
setup.py
doona/__init__.py
doona/wrapper.py
doona.egg-info/PKG-INFO
doona.egg-info/SOURCES.txt
doona.egg-info/dependency_links.txt
doona.egg-info/top_level.txt
doona/tests/test_wrapper.py