Metadata-Version: 2.1
Name: doona
Version: 0.0.1
Summary: Python implementation of quilt
Home-page: https://github.com/breezy-team/doona
Maintainer: Breezy Team
Maintainer-email: breezy-core@googlegroups.com
License: UNKNOWN
Platform: UNKNOWN
License-File: COPYING
License-File: AUTHORS
